{"Mutual Exclusion":{"Mutual Exclusion":{"internalLink":{"count":1,"lastUpdated":1739293424790}}},"cannot":{"cannot":{"currentFile":{"count":1,"lastUpdated":1739293462495}}},"ready":{"ready":{"currentFile":{"count":1,"lastUpdated":1739293601266}}},"Yield":{"Yield":{"currentFile":{"count":1,"lastUpdated":1739293606642}}},"Spin Locks":{"Spin Locks":{"internalLink":{"count":1,"lastUpdated":1739293619676}}},"spinning":{"spinning":{"currentFile":{"count":1,"lastUpdated":1739293652150}}},"until":{"until":{"currentFile":{"count":1,"lastUpdated":1739293653940}}},"locks":{"locks":{"currentFile":{"count":1,"lastUpdated":1739293662137}}},"task":{"task":{"internalLink":{"count":1,"lastUpdated":1739294212904}}},"Truthy and Falsie":{"Truthy and Falsie":{"internalLink":{"count":3,"lastUpdated":1739294418821}}},"AtomicBoolean":{"AtomicBoolean":{"currentFile":{"count":1,"lastUpdated":1739294565457}}},"Threads in Java Lecture 1":{"Threads in Java Lecture 1":{"internalLink":{"count":1,"lastUpdated":1739294683473}}},"space":{"space":{"currentFile":{"count":2,"lastUpdated":1739295559393}}},"Cache Coherence":{"Cache Coherence":{"internalLink":{"count":1,"lastUpdated":1739295211124}}},"lock":{"lock":{"internalLink":{"count":2,"lastUpdated":1739296261445}}},"Fairness":{"Fairness":{"internalLink":{"count":1,"lastUpdated":1739296568932}}},"ALock":{"ALock":{"currentFile":{"count":1,"lastUpdated":1739297316927}}},"volatile":{"volatile":{"internalLink":{"count":1,"lastUpdated":1739297391979}}}}